sunwaee_gen/__init__.py
sunwaee_gen/_completion.py
sunwaee_gen/agent.py
sunwaee_gen/api.py
sunwaee_gen/helpers.py
sunwaee_gen/logger.py
sunwaee_gen/message.py
sunwaee_gen/model.py
sunwaee_gen/provider.py
sunwaee_gen/response.py
sunwaee_gen/tool.py
sunwaee_gen/tool_call.py
sunwaee_gen/agents/__init__.py
sunwaee_gen/agents/_registry.py
sunwaee_gen/agents/anthropic.py
sunwaee_gen/agents/deepseek.py
sunwaee_gen/agents/google.py
sunwaee_gen/agents/openai.py
sunwaee_gen/agents/xai.py
sunwaee_gen/models/__init__.py
sunwaee_gen/models/_registry.py
sunwaee_gen/models/anthropic.py
sunwaee_gen/models/deepseek.py
sunwaee_gen/models/google.py
sunwaee_gen/models/openai.py
sunwaee_gen/models/xai.py
sunwaee_gen/providers/__init__.py
sunwaee_gen/providers/_registry.py
sunwaee_gen/providers/anthropic.py
sunwaee_gen/providers/deepseek.py
sunwaee_gen/providers/google.py
sunwaee_gen/providers/openai.py
sunwaee_gen/providers/xai.py
sunwaee_gen/tools/__init__.py
sunwaee_gen/tools/_registry.py
sunwaee_gen/tools/execute_command.py
sunwaee_gen-0.1.1.dist-info/licenses/LICENSE
sunwaee_gen-0.1.1.dist-info/METADATA
sunwaee_gen-0.1.1.dist-info/WHEEL
sunwaee_gen-0.1.1.dist-info/top_level.txt
sunwaee_gen-0.1.1.dist-info/RECORD
