Metadata-Version: 2.4
Name: sunwaee-gen
Version: 0.1.1
Summary: All LLMs, one response format.
Author: David NAISSE
Maintainer: David NAISSE
License: MIT License
Requires-Python: >=3.10
License-File: LICENSE
Requires-Dist: aiohttp
Requires-Dist: fastapi[standard]
Requires-Dist: pydantic
Requires-Dist: python-dotenv
Requires-Dist: rich
Requires-Dist: typer[all]
Requires-Dist: uvicorn[standard]
Provides-Extra: dev
Requires-Dist: pytest; extra == "dev"
Requires-Dist: pytest-cov; extra == "dev"
Requires-Dist: pytest-asyncio; extra == "dev"
Requires-Dist: httpx; extra == "dev"
Requires-Dist: twine; extra == "dev"
Requires-Dist: build; extra == "dev"
Dynamic: license-file
